villas/dataprocessing/__init__.py
villas/dataprocessing/plottools.py
villas/dataprocessing/readtools.py
villas/dataprocessing/timeseries.py
villas/dataprocessing/validationtools.py
villas_dataprocessing-0.2.6.dist-info/LICENSE
villas_dataprocessing-0.2.6.dist-info/METADATA
villas_dataprocessing-0.2.6.dist-info/WHEEL
villas_dataprocessing-0.2.6.dist-info/top_level.txt
villas_dataprocessing-0.2.6.dist-info/RECORD
