Metadata-Version: 2.1
Name: villas-dataprocessing
Version: 0.2.6
Summary: Several tools for processing simulation results
Home-page: https://git.rwth-aachen.de/acs/public/villas/dataprocessing
Author: Markus Mirz, Jan Dinkelbach, Steffen Vogel
Author-email: acs-software@eonerc.rwth-aachen.de
License: GPL-3.0
Keywords: simulation power system real-time data processing
Platform: UNKNOWN
Classifier: Development Status :: 4 - Beta
Classifier: Topic :: Scientific/Engineering
Classifier: License :: OSI Approved :: GNU General Public License v3 or later (GPLv3+)
Classifier: Operating System :: MacOS :: MacOS X
Classifier: Operating System :: Microsoft :: Windows
Classifier: Operating System :: POSIX :: Linux
Classifier: Programming Language :: Python :: 3
Requires-Dist: matplotlib
Requires-Dist: numpy
Requires-Dist: pandas
Requires-Dist: scipy
